{
    "s": 1,
    "d": {
        "Datacnt": 132,
        "Pagecnt": 7,
        "Com": [
            {
                "id": 338,
                "scocode": "2",
                "enable": true,
                "sconame": "测试0929",
                "scosimple": "1",
                "typelist": "11",
                "remark": "154444444",
                "creator": "管理员",
                "createdate": "2016-09-28T15:20:10"
            },
            {
                "id": 337,
                "scocode": "3",
                "enable": true,
                "sconame": "test092703",
                "scosimple": "2",
                "typelist": "1",
                "remark": "44",
                "creator": "管理员",
                "createdate": "2016-09-27T14:16:51"
            },
            {
                "id": 333,
                "scocode": "3",
                "enable": true,
                "sconame": "test092702",
                "scosimple": "2",
                "typelist": "1",
                "remark": "44",
                "creator": "管理员",
                "createdate": "2016-09-27T14:10:29"
            },
            {
                "id": 332,
                "scocode": "3",
                "enable": true,
                "sconame": "test0927",
                "scosimple": "2",
                "typelist": "1",
                "remark": "44",
                "creator": "管理员",
                "createdate": "2016-09-27T14:09:21"
            },
            {
                "id": 331,
                "scocode": "0511fff",
                "enable": true,
                "sconame": "test0511",
                "scosimple": "0511ffffff",
                "typelist": "0,2",
                "remark": "2222222",
                "creator": "系统管理员",
                "createdate": "2016-05-11T08:52:55"
            },
            {
                "id": 330,
                "scocode": "T26",
                "enable": true,
                "sconame": "测试资料26",
                "scosimple": "26",
                "typelist": "0,2",
                "remark": "test",
                "creator": "系统管理员",
                "createdate": "2016-05-04T16:08:47"
            },
            {
                "id": 329,
                "scocode": "T25",
                "enable": true,
                "sconame": "测试资料25",
                "scosimple": "25",
                "typelist": "0,1,2",
                "remark": "rer2222",
                "creator": "系统管理员",
                "createdate": "2016-05-04T16:01:23"
            },
            {
                "id": 328,
                "scocode": "T19",
                "enable": true,
                "sconame": "测试资料19",
                "scosimple": "19",
                "typelist": "1",
                "remark": "4444",
                "creator": "系统管理员",
                "createdate": "2016-05-04T15:30:45"
            },
            {
                "id": 327,
                "scocode": "T24",
                "enable": false,
                "sconame": "测试资料24",
                "scosimple": "24",
                "typelist": "1",
                "remark": "ffff",
                "creator": "系统管理员",
                "createdate": "2016-05-04T15:02:38"
            },
            {
                "id": 326,
                "scocode": "T23",
                "enable": false,
                "sconame": "测试资料23",
                "scosimple": "23",
                "typelist": "1",
                "remark": "",
                "creator": "系统管理员",
                "createdate": "2016-05-04T15:02:01"
            },
            {
                "id": 325,
                "scocode": "T22",
                "enable": false,
                "sconame": "测试资料22",
                "scosimple": "22",
                "typelist": "1",
                "remark": "",
                "creator": "系统管理员",
                "createdate": "2016-05-04T14:46:22"
            },
            {
                "id": 324,
                "scocode": "T21",
                "enable": false,
                "sconame": "测试资料21",
                "scosimple": "21",
                "typelist": "1",
                "remark": "",
                "creator": "系统管理员",
                "createdate": "2016-05-04T14:45:29"
            },
            {
                "id": 323,
                "scocode": "T20",
                "enable": false,
                "sconame": "测试资料20",
                "scosimple": "20",
                "typelist": "0",
                "remark": "",
                "creator": "系统管理员",
                "createdate": "2016-05-04T14:40:53"
            },
            {
                "id": 322,
                "scocode": "199",
                "enable": true,
                "sconame": "199",
                "scosimple": "",
                "typelist": "",
                "remark": "",
                "creator": "",
                "createdate": "2016-05-04T13:57:00"
            },
            {
                "id": 321,
                "scocode": "198",
                "enable": true,
                "sconame": "198",
                "scosimple": "",
                "typelist": "",
                "remark": "",
                "creator": "",
                "createdate": "2016-05-04T13:57:00"
            },
            {
                "id": 320,
                "scocode": "197",
                "enable": true,
                "sconame": "197",
                "scosimple": "",
                "typelist": "",
                "remark": "",
                "creator": "",
                "createdate": "2016-05-04T13:57:00"
            },
            {
                "id": 319,
                "scocode": "196",
                "enable": true,
                "sconame": "196",
                "scosimple": "",
                "typelist": "",
                "remark": "",
                "creator": "",
                "createdate": "2016-05-04T13:57:00"
            },
            {
                "id": 318,
                "scocode": "195",
                "enable": true,
                "sconame": "195",
                "scosimple": "",
                "typelist": "",
                "remark": "",
                "creator": "",
                "createdate": "2016-05-04T13:57:00"
            },
            {
                "id": 317,
                "scocode": "194",
                "enable": true,
                "sconame": "194",
                "scosimple": "",
                "typelist": "",
                "remark": "",
                "creator": "",
                "createdate": "2016-05-04T13:57:00"
            },
            {
                "id": 316,
                "scocode": "193",
                "enable": true,
                "sconame": "193",
                "scosimple": "",
                "typelist": "",
                "remark": "",
                "creator": "",
                "createdate": "2016-05-04T13:57:00"
            }
        ]
    },
    "m": ""
}