{
    "s": 1,
    "d": {
        "_receivedate": "2016-10-19",
        "id": 58,
        "scoid": 1,
        "sconame": "携云供应链管理",
        "purchaseid": 36,
        "warehouseid": 137,
        "warehousename": "南极云商常熟进货1仓",
        "remark": "remark1111",
        "logisticsno": "",
        "finconfirmer": "",
        "status": 0,
        "finstatus": 0,
        "creator": "管理员",
        "createdate": "2016-10-19T15:15:14",
        "modifier": "管理员",
        "modifydate": "2016-10-19T15:23:13",
        "finconfirmdate": "0001-01-01T00:00:00",
        "coid": 1,
        "receivedate": "2016-10-19"
    },
    "m": ""
}